{
	"title": {
		"ru": "Четверг - день ПвП",
		"en": "Thursday is PvP day"
	},
	"description": {
		"ru": [
			"Четверг - день ПвП, каждому начислены бонусные $BRO в зависимости от уровня.",
			"Только СЕГОДНЯ, при победе или поражении получаешь/теряешь в два раза больше $BRO. Начало 24.10 в 00:00 по UTC +3, окончание 25.10 в 00:00.",
			"Удачи в боях, бро! 👊"
		],
		"en": [
			"Thursday is PvP day, so everyone got bonus $BRO based on their level.",
			"Only TODAY, win or lose, you'll gain or lose double the $BRO. Starts 24.10 at 00:00 UTC +3, ends 25.10 at 00:00.",
			"Good luck in battles, bro! 👊"
		]
	}
}
